enccomslice/__init__.py
enccomslice/websocket.py
enccomslice-0.2.dist-info/LICENSE
enccomslice-0.2.dist-info/METADATA
enccomslice-0.2.dist-info/WHEEL
enccomslice-0.2.dist-info/top_level.txt
enccomslice-0.2.dist-info/RECORD
