Metadata-Version: 2.1
Name: enccomslice
Version: 0.2
Summary: A simple library
Home-page: https://github.com/prathaaccount/enccomslice
Author: soniya
Author-email: prathpatil28@gmail.com
License: UNKNOWN
Platform: UNKNOWN
Classifier: Programming Language :: Python :: 3
Classifier: License :: OSI Approved :: MIT License
Classifier: Operating System :: OS Independent
Requires-Dist: websockets
